np_zoom_in/LICENSE
np_zoom_in/README.MD
np_zoom_in/__init__.py
np_zoom_in/requirements.txt
np_zoom_in/thirdparty.json
np_zoom_in-0.10.dist-info/LICENSE.rst
np_zoom_in-0.10.dist-info/METADATA
np_zoom_in-0.10.dist-info/WHEEL
np_zoom_in-0.10.dist-info/top_level.txt
np_zoom_in-0.10.dist-info/RECORD
